tagmap.cpython-311-x86_64-linux-gnu.so
tagmap/stress_tagmap.cc
tagmap/tagmap.cc
tagmap/tagmap.h
tagmap/test_tagmap.cc
tagmap-0.1.17.dist-info/METADATA
tagmap-0.1.17.dist-info/WHEEL
tagmap-0.1.17.dist-info/top_level.txt
tagmap-0.1.17.dist-info/RECORD
tagmap-0.1.17.dist-info/licenses/LICENSE
