Metadata-Version: 2.4
Name: tagmap
Version: 0.1.17
Summary: Fast data structure for managing tags and metadata with efficient queries
Author: originalsouth
License: UNICODE
Project-URL: Homepage, https://github.com/originalsouth/tagmap.py
Project-URL: Repository, https://github.com/originalsouth/tagmap.py
Keywords: tags,metadata,data-structure,c++
Classifier: Development Status :: 3 - Alpha
Classifier: Intended Audience :: Developers
Classifier: License :: OSI Approved :: MIT License
Classifier: Programming Language :: Python :: 3
Classifier: Programming Language :: Python :: 3.8
Classifier: Programming Language :: Python :: 3.9
Classifier: Programming Language :: Python :: 3.10
Classifier: Programming Language :: Python :: 3.11
Classifier: Programming Language :: Python :: 3.12
Classifier: Programming Language :: Python :: 3.13
Classifier: Programming Language :: Python :: 3.14
Classifier: Topic :: Software Development :: Libraries :: Python Modules
Requires-Python: >=3.8
License-File: LICENSE
Dynamic: license-file
